[
      {
            "id": 1,
            "firstName": "T00001",
            "lastName": "Kandy WB",
            "gender": "male",
            "address": "1234 Peradeniya St.",
            "city": " Peradeniya ",
            "state": {
                "abbreviation": "KA",
                "name": "Kandy"
            },
            "orders": [
                {"productName": "2016", "itemCost": 26000000},
                {"productName": "2017", "itemCost": 20480000}
            ],
            "latitude": 7.2658414,
            "longitude": 80.5896306
      }
]
